<?xml version="1.0" ?>
<annotation>
	<folder>text</folder>
	<filename>img_993.jpg</filename>
	<source>
		<database>coco_text_database</database>
		<annotation>text</annotation>
		<image>text</image>
		<flickrid>000000</flickrid>
	</source>
	<owner>
		<name>ms</name>
	</owner>
	<size>
		<width>600</width>
		<height>793</height>
		<depth>3</depth>
	</size>
	<segmented>0</segmented>
	<object>
		<name>text</name>
		<pose>none</pose>
		<truncated>0</truncated>
		<difficult>0</difficult>
		<bndbox>
			<xmin>290</xmin>
			<ymin>308</ymin>
			<xmax>304</xmax>
			<ymax>504</ymax>
		</bndbox>
	</object>
	<object>
		<name>text</name>
		<pose>none</pose>
		<truncated>0</truncated>
		<difficult>0</difficult>
		<bndbox>
			<xmin>305</xmin>
			<ymin>308</ymin>
			<xmax>320</xmax>
			<ymax>504</ymax>
		</bndbox>
	</object>
	<object>
		<name>text</name>
		<pose>none</pose>
		<truncated>0</truncated>
		<difficult>0</difficult>
		<bndbox>
			<xmin>321</xmin>
			<ymin>308</ymin>
			<xmax>326</xmax>
			<ymax>504</ymax>
		</bndbox>
	</object>
</annotation>
